Metadata-Version: 2.1
Name: chunkedfile
Version: 0.3.0
Summary: Save file writes into multiple chunks.
Home-page: http://github.com/danijar/chunkedfile
License: UNKNOWN
Platform: UNKNOWN
Classifier: License :: OSI Approved :: MIT License
Classifier: Programming Language :: Python :: 3
